gmail_fakex/Gmail_Fakex.py
gmail_fakex/__init__.py
gmail_fakex-0.1.0.dist-info/METADATA
gmail_fakex-0.1.0.dist-info/WHEEL
gmail_fakex-0.1.0.dist-info/top_level.txt
gmail_fakex-0.1.0.dist-info/RECORD
