Metadata-Version: 2.1
Name: gmail-fakex
Version: 0.1.0
Summary: Temporary Gmail-like email generator using mail.tm API
Home-page: https://github.com/ali-88-bot/Gmail_Fakex
Author: Ali Nedaiy
Author-email: alinedaiy88@gmail.com
Requires-Python: >=3.6
Requires-Dist: requests
Requires-Dist: colorama
Requires-Dist: plyer
Requires-Dist: beautifulsoup4
